<?xml version="1.0" encoding="utf-8"?>
<gamelist>
	<game>
		<path>./Koboo The Tree Spirit - Prologue.sh</path>
		<name>Koboo The Tree Spirit : Prologue</name>
		<desc>Explore the free prologue of Koboo: The Tree Spirit! An action rogue-lite platformer where you battle against towering hunters as a tiny spirit. Forge powerful synergies, battle seemingly gigantic bosses and rebuild your home.</desc>
		<image>./koboo_prologue/cover.png</image>
		<thumbnail>./koboo_prologue/thumb.png</thumbnail>
		<releasedate>20240625</releasedate>
		<developer>Jerome Labelle, Simon Labelle</developer>
		<genre>Action, Adventure, Indie, RPG</genre>
	</game>
</gamelist>